elgato/__init__.py
elgato/elgato.py
elgato/exceptions.py
elgato/models.py
elgato/py.typed
elgato-5.1.1.dist-info/METADATA
elgato-5.1.1.dist-info/WHEEL
elgato-5.1.1.dist-info/RECORD
