Metadata-Version: 2.1
Name: elgato
Version: 5.1.1
Summary: Asynchronous Python client for Elgato Lights.
Home-page: https://github.com/frenck/python-elgato
License: MIT
Keywords: elgato,keylight,api,async,client
Author: Franck Nijhof
Author-email: opensource@frenck.dev
Maintainer: Franck Nijhof
Maintainer-email: opensource@frenck.dev
Requires-Python: >=3.11,<4.0
Classifier: Development Status :: 5 - Production/Stable
Classifier: Framework :: AsyncIO
Classifier: Intended Audience :: Developers
Classifier: License :: OSI Approved :: MIT License
Classifier: Natural Language :: English
Classifier: Programming Language :: Python :: 3
Classifier: Programming Language :: Python :: 3.11
Classifier: Programming Language :: Python :: 3.12
Classifier: Topic :: Software Development :: Libraries :: Python Modules
Requires-Dist: aiohttp (>=3.0.0)
Requires-Dist: mashumaro (>=3.10)
Requires-Dist: orjson (>=3.9.8)
Requires-Dist: yarl (>=1.6.0)
Project-URL: Bug Tracker, https://github.com/frenck/python-elgato/issues
Project-URL: Changelog, https://github.com/frenck/python-elgato/releases
Project-URL: Documentation, https://github.com/frenck/python-elgato
Project-URL: Repository, https://github.com/frenck/python-elgato
